{
    "week": 295,
    "satellites": [
        {
            "ID": "02",
            "Health": "000",
            "Eccentricity": 0.01646327972,
            "TimeOfApplicability": 147456.0,
            "OrbitalInclination": 0.9664043011,
            "RateOfRightAscen": -8.137481816e-09,
            "SQRT_A": 5153.631348,
            "RightAscenAtWeek": -1.445212136,
            "ArgumentOfPerigee": -1.088006958,
            "MeanAnom": -1.683568632,
            "Af0": -0.000301361084,
            "Af1": 7.275957614e-12
        },
        {
            "ID": "03",
            "Health": "000",
            "Eccentricity": 0.005651950836,
            "TimeOfApplicability": 147456.0,
            "OrbitalInclination": 0.9875324896,
            "RateOfRightAscen": -7.554600394e-09,
            "SQRT_A": 5153.581055,
            "RightAscenAtWeek": -0.3067860459,
            "ArgumentOfPerigee": 1.155244077,
            "MeanAnom": 1.119831067,
            "Af0": 0.0006151199341,
            "Af1": 1.091393642e-11
        },
        {
            "ID": "04",
            "Health": "000",
            "Eccentricity": 0.003190517426,
            "TimeOfApplicability": 147456.0,
            "OrbitalInclination": 0.966290451,
            "RateOfRightAscen": -7.577458489e-09,
            "SQRT_A": 5153.637207,
            "RightAscenAtWeek": 0.7693591509,
            "ArgumentOfPerigee": -2.991789093,
            "MeanAnom": -2.130518427,
            "Af0": 0.0004892349243,
            "Af1": 7.275957614e-12
        },
        {
            "ID": "05",
            "Health": "000",
            "Eccentricity": 0.005653381348,
            "TimeOfApplicability": 147456.0,
            "OrbitalInclination": 0.9743857949,
            "RateOfRightAscen": -7.714607059e-09,
            "SQRT_A": 5153.669434,
            "RightAscenAtWeek": -0.3605667532,
            "ArgumentOfPerigee": 1.334873377,
            "MeanAnom": -1.495969823,
            "Af0": -0.0001945495605,
            "Af1": 0.0
        },
        {
            "ID": "06",
            "Health": "000",
            "Eccentricity": 0.00333404541,
            "TimeOfApplicability": 147456.0,
            "OrbitalInclination": 0.9891383757,
            "RateOfRightAscen": -7.966046104e-09,
            "SQRT_A": 5153.695801,
            "RightAscenAtWeek": -1.342608445,
            "ArgumentOfPerigee": -0.758130681,
            "MeanAnom": 2.551544097,
            "Af0": -1.335144043e-05,
            "Af1": -2.910383046e-11
        },
        {
            "ID": "07",
            "Health": "000",
            "Eccentricity": 0.01887607574,
            "TimeOfApplicability": 147456.0,
            "OrbitalInclination": 0.9498720628,
            "RateOfRightAscen": -7.966046104e-09,
            "SQRT_A": 5153.518066,
            "RightAscenAtWeek": 1.781355413,
            "ArgumentOfPerigee": -2.091441615,
            "MeanAnom": 1.702256907,
            "Af0": -1.71661377e-05,
            "Af1": 0.0
        },
        {
            "ID": "08",
            "Health": "000",
            "Eccentricity": 0.0100736618,
            "TimeOfApplicability": 147456.0,
            "OrbitalInclination": 0.9505012347,
            "RateOfRightAscen": -7.863184676e-09,
            "SQRT_A": 5153.672363,
            "RightAscenAtWeek": -2.445608043,
            "ArgumentOfPerigee": 0.383117319,
            "MeanAnom": -1.813384378,
            "Af0": 0.0004291534424,
            "Af1": 1.091393642e-11
        },
        {
            "ID": "09",
            "Health": "000",
            "Eccentricity": 0.003170013428,
            "TimeOfApplicability": 147456.0,
            "OrbitalInclination": 0.9601005988,
            "RateOfRightAscen": -7.623174679e-09,
            "SQRT_A": 5153.505371,
            "RightAscenAtWeek": 0.7083946498,
            "ArgumentOfPerigee": 2.027057865,
            "MeanAnom": -1.27337408,
            "Af0": 0.000470161438,
            "Af1": 1.818989404e-11
        },
        {
            "ID": "10",
            "Health": "000",
            "Eccentricity": 0.01003694534,
            "TimeOfApplicability": 147456.0,
            "OrbitalInclination": 0.9871609786,
            "RateOfRightAscen": -7.543171346e-09,
            "SQRT_A": 5153.647461,
            "RightAscenAtWeek": -0.3093169644,
            "ArgumentOfPerigee": -2.351917994,
            "MeanAnom": 0.1420100691,
            "Af0": -0.0002183914185,
            "Af1": -1.455191523e-11
        },
        {
            "ID": "11",
            "Health": "000",
            "Eccentricity": 0.001762390137,
            "TimeOfApplicability": 147456.0,
            "OrbitalInclination": 0.9658170741,
            "RateOfRightAscen": -8.194627053e-09,
            "SQRT_A": 5153.529297,
            "RightAscenAtWeek": -1.313742193,
            "ArgumentOfPerigee": -2.381978925,
            "MeanAnom": -2.717669797,
            "Af0": -0.0007524490356,
            "Af1": 0.0
        },
        {
            "ID": "12",
            "Health": "000",
            "Eccentricity": 0.00888633728,
            "TimeOfApplicability": 147456.0,
            "OrbitalInclination": 0.9615746585,
            "RateOfRightAscen": -7.588887536e-09,
            "SQRT_A": 5153.737793,
            "RightAscenAtWeek": 2.897460885,
            "ArgumentOfPerigee": 1.458424744,
            "MeanAnom": 0.9809159241,
            "Af0": -0.0005559921265,
            "Af1": -3.637978807e-12
        },
        {
            "ID": "13",
            "Health": "000",
            "Eccentricity": 0.00877904892,
            "TimeOfApplicability": 147456.0,
            "OrbitalInclination": 0.9724683189,
            "RateOfRightAscen": -7.520313251e-09,
            "SQRT_A": 5153.638184,
            "RightAscenAtWeek": 0.8771190542,
            "ArgumentOfPerigee": 0.974266926,
            "MeanAnom": -2.120298505,
            "Af0": 0.0006885528564,
            "Af1": 0.0
        },
        {
            "ID": "14",
            "Health": "000",
            "Eccentricity": 0.005049228668,
            "TimeOfApplicability": 147456.0,
            "OrbitalInclination": 0.9448626568,
            "RateOfRightAscen": -7.737465154e-09,
            "SQRT_A": 5153.646484,
            "RightAscenAtWeek": 2.850072638,
            "ArgumentOfPerigee": -2.860500786,
            "MeanAnom": 0.8180866349,
            "Af0": 0.0005521774292,
            "Af1": 7.275957614e-12
        },
        {
            "ID": "15",
            "Health": "000",
            "Eccentricity": 0.01613426208,
            "TimeOfApplicability": 147456.0,
            "OrbitalInclination": 0.9373785084,
            "RateOfRightAscen": -7.817468486e-09,
            "SQRT_A": 5153.678711,
            "RightAscenAtWeek": 0.5756869608,
            "ArgumentOfPerigee": 1.381523845,
            "MeanAnom": -2.829450034,
            "Af0": 0.0002346038818,
            "Af1": 3.637978807e-12
        },
        {
            "ID": "16",
            "Health": "000",
            "Eccentricity": 0.01432180405,
            "TimeOfApplicability": 147456.0,
            "OrbitalInclination": 0.9609574709,
            "RateOfRightAscen": -7.600316584e-09,
            "SQRT_A": 5153.609863,
            "RightAscenAtWeek": 2.915084811,
            "ArgumentOfPerigee": 0.856780701,
            "MeanAnom": -0.8214324806,
            "Af0": -0.0001134872437,
            "Af1": 1.091393642e-11
        },
        {
            "ID": "17",
            "Health": "000",
            "Eccentricity": 0.01349544525,
            "TimeOfApplicability": 147456.0,
            "OrbitalInclination": 0.9662245377,
            "RateOfRightAscen": -7.760323249e-09,
            "SQRT_A": 5153.543457,
            "RightAscenAtWeek": -2.347937359,
            "ArgumentOfPerigee": -1.261531419,
            "MeanAnom": -1.866729534,
            "Af0": 0.0005359649658,
            "Af1": -1.455191523e-11
        },
        {
            "ID": "18",
            "Health": "000",
            "Eccentricity": 0.004799842834,
            "TimeOfApplicability": 147456.0,
            "OrbitalInclination": 0.9740322603,
            "RateOfRightAscen": -8.114623721e-09,
            "SQRT_A": 5153.672852,
            "RightAscenAtWeek": -1.341219399,
            "ArgumentOfPerigee": -2.941659829,
            "MeanAnom": 2.430923623,
            "Af0": -0.0006608963013,
            "Af1": 0.0
        },
        {
            "ID": "19",
            "Health": "000",
            "Eccentricity": 0.009961605072,
            "TimeOfApplicability": 147456.0,
            "OrbitalInclination": 0.9654036183,
            "RateOfRightAscen": -7.794610391e-09,
            "SQRT_A": 5153.55127,
            "RightAscenAtWeek": -2.303715569,
            "ArgumentOfPerigee": 2.688570976,
            "MeanAnom": 0.0009501243308,
            "Af0": 0.0005693435669,
            "Af1": 3.637978807e-12
        },
        {
            "ID": "20",
            "Health": "000",
            "Eccentricity": 0.00386095047,
            "TimeOfApplicability": 147456.0,
            "OrbitalInclination": 0.9566012051,
            "RateOfRightAscen": -7.966046104e-09,
            "SQRT_A": 5153.602539,
            "RightAscenAtWeek": -0.4926370312,
            "ArgumentOfPerigee": -2.429405746,
            "MeanAnom": 2.845575557,
            "Af0": 0.0003681182861,
            "Af1": 0.0
        },
        {
            "ID": "21",
            "Health": "000",
            "Eccentricity": 0.02566719055,
            "TimeOfApplicability": 147456.0,
            "OrbitalInclination": 0.960645881,
            "RateOfRightAscen": -8.183198006e-09,
            "SQRT_A": 5153.57959,
            "RightAscenAtWeek": -1.453535555,
            "ArgumentOfPerigee": -0.485018435,
            "MeanAnom": -2.00095435,
            "Af0": 9.632110596e-05,
            "Af1": 0.0
        },
        {
            "ID": "22",
            "Health": "000",
            "Eccentricity": 0.01368570328,
            "TimeOfApplicability": 147456.0,
            "OrbitalInclination": 0.9603163148,
            "RateOfRightAscen": -7.554600394e-09,
            "SQRT_A": 5153.633301,
            "RightAscenAtWeek": 2.918379349,
            "ArgumentOfPerigee": -1.083043616,
            "MeanAnom": -1.342872473,
            "Af0": -8.392333984e-05,
            "Af1": -3.637978807e-12
        },
        {
            "ID": "23",
            "Health": "000",
            "Eccentricity": 0.004950523376,
            "TimeOfApplicability": 147456.0,
            "OrbitalInclination": 0.9822654228,
            "RateOfRightAscen": -7.611745631e-09,
            "SQRT_A": 5153.586914,
            "RightAscenAtWeek": -0.3392063703,
            "ArgumentOfPerigee": -2.890563589,
            "MeanAnom": 1.311082069,
            "Af0": 0.0003757476807,
            "Af1": 7.275957614e-12
        },
        {
            "ID": "24",
            "Health": "000",
            "Eccentricity": 0.0163564682,
            "TimeOfApplicability": 147456.0,
            "OrbitalInclination": 0.9336094696,
            "RateOfRightAscen": -8.137481816e-09,
            "SQRT_A": 5153.620605,
            "RightAscenAtWeek": 1.680950454,
            "ArgumentOfPerigee": 1.036116762,
            "MeanAnom": 2.573750492,
            "Af0": -0.0004768371582,
            "Af1": 3.637978807e-12
        },
        {
            "ID": "25",
            "Health": "000",
            "Eccentricity": 0.01215744019,
            "TimeOfApplicability": 147456.0,
            "OrbitalInclination": 0.9495844414,
            "RateOfRightAscen": -7.703178011e-09,
            "SQRT_A": 5153.647949,
            "RightAscenAtWeek": 2.808812824,
            "ArgumentOfPerigee": 1.10006571,
            "MeanAnom": 0.7827174421,
            "Af0": 0.0004987716675,
            "Af1": 0.0
        },
        {
            "ID": "26",
            "Health": "000",
            "Eccentricity": 0.00966501236,
            "TimeOfApplicability": 147456.0,
            "OrbitalInclination": 0.9302958315,
            "RateOfRightAscen": -7.931758961e-09,
            "SQRT_A": 5153.678711,
            "RightAscenAtWeek": 2.742835921,
            "ArgumentOfPerigee": 0.587589918,
            "MeanAnom": 0.01552893393,
            "Af0": 5.722045898e-06,
            "Af1": -1.455191523e-11
        },
        {
            "ID": "27",
            "Health": "000",
            "Eccentricity": 0.01292943954,
            "TimeOfApplicability": 147456.0,
            "OrbitalInclination": 0.9595313481,
            "RateOfRightAscen": -7.806039439e-09,
            "SQRT_A": 5153.641602,
            "RightAscenAtWeek": -2.417508781,
            "ArgumentOfPerigee": 0.800646966,
            "MeanAnom": -1.744260867,
            "Af0": -3.433227539e-05,
            "Af1": 0.0
        },
        {
            "ID": "28",
            "Health": "000",
            "Eccentricity": 0.0004806518555,
            "TimeOfApplicability": 147456.0,
            "OrbitalInclination": 0.9609215182,
            "RateOfRightAscen": -7.840326581e-09,
            "SQRT_A": 5153.704102,
            "RightAscenAtWeek": 1.750430495,
            "ArgumentOfPerigee": 1.421113358,
            "MeanAnom": 0.4757321585,
            "Af0": -0.0004968643188,
            "Af1": -1.091393642e-11
        },
        {
            "ID": "29",
            "Health": "000",
            "Eccentricity": 0.002862453461,
            "TimeOfApplicability": 147456.0,
            "OrbitalInclination": 0.9687112644,
            "RateOfRightAscen": -7.771752296e-09,
            "SQRT_A": 5153.696777,
            "RightAscenAtWeek": -2.332433892,
            "ArgumentOfPerigee": 2.664604024,
            "MeanAnom": -1.906944847,
            "Af0": -0.0005588531494,
            "Af1": 3.637978807e-12
        },
        {
            "ID": "30",
            "Health": "000",
            "Eccentricity": 0.007171154022,
            "TimeOfApplicability": 147456.0,
            "OrbitalInclination": 0.9350355924,
            "RateOfRightAscen": -8.126052768e-09,
            "SQRT_A": 5153.698242,
            "RightAscenAtWeek": 1.779140204,
            "ArgumentOfPerigee": -2.46117293,
            "MeanAnom": 1.53185958,
            "Af0": -0.0002698898315,
            "Af1": 7.275957614e-12
        },
        {
            "ID": "31",
            "Health": "000",
            "Eccentricity": 0.01072740555,
            "TimeOfApplicability": 147456.0,
            "OrbitalInclination": 0.9538028886,
            "RateOfRightAscen": -7.920329914e-09,
            "SQRT_A": 5153.530762,
            "RightAscenAtWeek": 1.80367416,
            "ArgumentOfPerigee": 0.779935604,
            "MeanAnom": 0.6280348042,
            "Af0": -0.0002202987671,
            "Af1": 0.0
        },
        {
            "ID": "32",
            "Health": "000",
            "Eccentricity": 0.008105278015,
            "TimeOfApplicability": 147456.0,
            "OrbitalInclination": 0.9633962606,
            "RateOfRightAscen": -7.554600394e-09,
            "SQRT_A": 5153.710449,
            "RightAscenAtWeek": 0.7237588006,
            "ArgumentOfPerigee": -2.127265834,
            "MeanAnom": -1.131589464,
            "Af0": -0.0005655288696,
            "Af1": 7.275957614e-12
        }
    ]
}